protoc_wrapper/__init__.py
protoc_wrapper/__main__.py
protoc_wrapper/protoc
protoc_wrapper-33.0.0.dist-info/entry_points.txt
protoc_wrapper-33.0.0.dist-info/METADATA
protoc_wrapper-33.0.0.dist-info/WHEEL
protoc_wrapper-33.0.0.dist-info/licenses/LICENSE
protoc_wrapper-33.0.0.dist-info/RECORD
