Metadata-Version: 2.4
Name: protoc-wrapper
Version: 33.0.0
Summary: Repackage official protoc compiler as Python wheels
Keywords: protobuf,protoc
Author: j178
Author-email: j178 <10510431+j178@users.noreply.github.com>
License-Expression: MIT
Classifier: Development Status :: 4 - Beta
Classifier: Environment :: Console
Classifier: Intended Audience :: Developers
Classifier: Operating System :: OS Independent
Classifier: License :: OSI Approved :: MIT License
Classifier: Programming Language :: Python
Classifier: Programming Language :: Python :: 3.8
Classifier: Programming Language :: Python :: 3.9
Classifier: Programming Language :: Python :: 3.10
Classifier: Programming Language :: Python :: 3.11
Classifier: Programming Language :: Python :: 3.12
Classifier: Programming Language :: Python :: 3.13
Classifier: Programming Language :: Python :: 3 :: Only
Classifier: Topic :: Software Development :: Code Generators
Requires-Python: >=3.8
Project-URL: Releases, https://github.com/j178/protoc-wrapper/releases
Project-URL: Repository, https://github.com/j178/protoc-wrapper
